MANIFEST.in
README.rst
setup.cfg
setup.py
pandocpm/__init__.py
pandocpm/__main__.py
pandocpm/tools.py
pandocpm/utils.py
pandocpm/version.py
pandocpm.egg-info/PKG-INFO
pandocpm.egg-info/SOURCES.txt
pandocpm.egg-info/dependency_links.txt
pandocpm.egg-info/entry_points.txt
pandocpm.egg-info/requires.txt
pandocpm.egg-info/top_level.txt