Metadata-Version: 1.1
Name: pandocpm
Version: 0.2.1
Summary: Package manager for pandoc extras (filters, templates, etc.)
Home-page: https://github.com/pandoc-extras/pandocpm
Author: Sergio Correia
Author-email: sergio.correia@gmail.com
License: Apache
Keywords: pandoc pandocfilters panflute markdown latex
Platform: UNKNOWN
Classifier: Development Status :: 3 - Alpha
Classifier: Environment :: Console
Classifier: Intended Audience :: End Users/Desktop
Classifier: Intended Audience :: Developers
Classifier: Topic :: Software Development :: Build Tools
Classifier: License :: OSI Approved :: Apache Software License
Classifier: Operating System :: OS Independent
Classifier: Topic :: Text Processing :: Filters
Classifier: Programming Language :: Python :: 3
Classifier: Programming Language :: Python :: 3.2
Classifier: Programming Language :: Python :: 3.3
Classifier: Programming Language :: Python :: 3.4
Classifier: Programming Language :: Python :: 3.5
